raster_footprint/__init__.py
raster_footprint/_cli.py
raster_footprint/constants.py
raster_footprint/densify.py
raster_footprint/footprint.py
raster_footprint/mask.py
raster_footprint/reproject.py
raster_footprint/simplify.py
raster_footprint-0.2.0.dist-info/LICENSE
raster_footprint-0.2.0.dist-info/METADATA
raster_footprint-0.2.0.dist-info/WHEEL
raster_footprint-0.2.0.dist-info/entry_points.txt
raster_footprint-0.2.0.dist-info/top_level.txt
raster_footprint-0.2.0.dist-info/RECORD
