Metadata-Version: 2.1
Name: raster-footprint
Version: 0.2.0
Summary: Create GeoJSON geometries that bound the extents of valid data in a raster.
Author-email: Preston Hartzell <preston.hartzell@gmail.com>
License: Apache-2.0
Project-URL: Documentation, https://raster-footprint.readthedocs.io
Project-URL: GitHub, https://github.com/pjhartzell/raster-footprint
Project-URL: Changelog, https://github.com/pjhartzell/raster-footprint/blob/main/CHANGELOG.md
Keywords: geojson,footprint,rasterio,shapely
Classifier: Programming Language :: Python :: 3
Classifier: Development Status :: 4 - Beta
Requires-Python: >=3.8
License-File: LICENSE
Requires-Dist: rasterio >=1.3
Requires-Dist: shapely >=2.0
Provides-Extra: dev
Requires-Dist: black ~=23.7 ; extra == 'dev'
Requires-Dist: codespell ~=2.2 ; extra == 'dev'
Requires-Dist: mypy ~=1.4 ; extra == 'dev'
Requires-Dist: pre-commit ~=3.3 ; extra == 'dev'
Requires-Dist: pytest ~=7.4 ; extra == 'dev'
Requires-Dist: ruff ==0.0.282 ; extra == 'dev'
Requires-Dist: sphinx-autobuild ~=2021.3 ; extra == 'dev'
Requires-Dist: tomli ~=2.0 ; (python_version < "3.11") and extra == 'dev'
Provides-Extra: docs
Requires-Dist: sphinx ~=7.1 ; extra == 'docs'
Requires-Dist: pydata-sphinx-theme ~=0.13 ; extra == 'docs'
